shapecms/__init__.py
shapecms/db.py
shapecms/page_views.py
shapecms/shape.py
shapecms/util.py
shapecms/fields/base.py
shapecms/fields/text.py
shapecms/static/css/general.css
shapecms/static/css/style.css
shapecms/static/fields/text/text.css
shapecms/static/js/htmx.js
shapecms/templates/admin/content.html
shapecms/templates/admin/content_edit.html
shapecms/templates/admin/login.html
shapecms/templates/admin/no_shapes_found.html
shapecms/templates/admin/setup.html
shapecms/templates/admin/partials/header.html
shapecms/templates/fields/text/editable.html
shapecms/templates/fields/text/viewable.html
shapecms/views/content.py
shapecms/views/content_add.py
shapecms/views/content_edit.py
shapecms/views/login.py
shapecms/views/main.py
shapecms/views/setup.py
shapecms/views/api/update_field.py
shapecms-0.0.11.dist-info/METADATA
shapecms-0.0.11.dist-info/WHEEL
shapecms-0.0.11.dist-info/licenses/LICENSE
shapecms-0.0.11.dist-info/RECORD
